<?xml version="1.0" encoding="UTF-8"?>
<openerp>
    <data>
    	<record id="inherit_view_task_kanban" model="ir.ui.view">
			<field name="name">inherit.view.task.kanban</field>
			<field name="model">project.task</field>
			<field name="inherit_id" ref="project.view_task_kanban" />
			<field name="arch" type="xml">
				<xpath expr="//div[@class='oe_kanban_content']/div" position="before">
					<div><field name="phisical_part"/></div>
				</xpath>
			</field>
		</record>
		<record id="inherit_view_task_form2" model="ir.ui.view">
			<field name="name">project.task.form.inherit</field>
			<field name="model">project.task</field>
			<field name="inherit_id" ref="project.view_task_form2" />
			<field name="arch" type="xml">
				<xpath expr="//header/field[@name='stage_id']" position="before">
	            	<button name="action_task_sent" type="object" string="Send by Email" class="oe_highlight" groups="base.group_user"/>
                </xpath>
				<xpath expr="//field[@name='categ_ids']" position="attributes">
					<attribute name="string">Servicio</attribute>				
				</xpath>
				<xpath expr="//field[@name='date_deadline']" position="before">
					<field name="phisical_part" string="Parte físico Nº"/>	
				</xpath>
				<xpath expr="//field[@name='categ_ids']" position="after">
					<field name="office"/>				
				</xpath>
				<xpath expr="//field[@name='partner_id']" position="replace"/>
				<xpath expr="//field[@name='project_id']" position="before">
					<field name="partner_id" domain="[('customer', '=', True)]"/>
				</xpath>
				<xpath expr="//field[@name='project_id']" position="attributes">
					<attribute name="domain">[('partner_id', '=', partner_id)]</attribute>
				</xpath>
	   	 	</field>
	   	 </record>
		 <record id="inherit_sign_view_task_form2" model="ir.ui.view">
			<field name="name">project.task.sign.form.inherit</field>
			<field name="model">project.task</field>
			<field name="inherit_id" ref="sd_digital_sign.inherit_view_task_form2" />
			<field name="arch" type="xml">
				<xpath expr="//group[@string='Signature']" position="before">
					<group>
						<field name="material_factured"/>
					</group>				
				</xpath>
				<xpath expr="//field[@name='signature_image']" position="after">
					<field name="signature_client"/>				
				</xpath>
				<xpath expr="//div[@class='col-xs-offset-9']" position="attributes">
					<attribute name="class">col-xs-offset-0</attribute>
				</xpath>
	   	 	</field>
	   	 </record>
	   	 
	   	 <record id="inherit_view_task_search_form" model="ir.ui.view">
	   	 	<field name="name">sd.project.task.search.form</field>
	   	 	<field name="model">project.task</field>
	   	 	<field name="inherit_id" ref="project.view_task_search_form"/>
	   	 	<field name="arch" type="xml">
	   	 		<xpath expr="//field[@name='name']" position="after">
	   	 			<field name="phisical_part" string="Parte Nº" filter_domain="['|',('id','=',self),('phisical_part','=',self)]"/>
	   	 		</xpath>
	   	 	</field>
	   	 </record>
	   	 
	   	 <menuitem name="Customer Support"
            id="menu_support"
            parent="base.menu_main_pm"
            sequence="0"/>
            
         <menuitem action="crm_helpdesk.crm_case_helpdesk_act111" 
         	name="Helpdesk" 
         	id="menu_helpdesk" 
         	parent="sd_sdatos_module.menu_support" 
         	sequence="10"/>
    </data>
</openerp>